yaflux/__init__.py
yaflux/_base.py
yaflux/_loaders.py
yaflux/_metadata.py
yaflux/_step.py
yaflux/py.typed
yaflux/_ast/__init__.py
yaflux/_ast/_assignment.py
yaflux/_ast/_error.py
yaflux/_ast/_results.py
yaflux/_ast/_utils.py
yaflux/_ast/_validation.py
yaflux/_executor/__init__.py
yaflux/_executor/_engine.py
yaflux/_executor/_error.py
yaflux/_graph/__init__.py
yaflux/_graph/_error.py
yaflux/_graph/_utils.py
yaflux/_graph/_validation.py
yaflux/_results/__init__.py
yaflux/_results/_error.py
yaflux/_results/_lock.py
yaflux/_results/_results.py
yaflux/_viz/__init__.py
yaflux/_viz/_check.py
yaflux/_viz/_impl.py
yaflux/_viz/_style.py
yaflux/_yax/__init__.py
yaflux/_yax/_error.py
yaflux/_yax/_tarfile.py
yaflux/_yax/_serializer/__init__.py
yaflux/_yax/_serializer/_base.py
yaflux/_yax/_serializer/_formats/__init__.py
yaflux/_yax/_serializer/_formats/_anndata.py
yaflux/_yax/_serializer/_formats/_numpy.py
yaflux/_yax/_serializer/_formats/_pandas.py
yaflux/_yax/_serializer/_formats/_pickle.py
yaflux-0.3.2.dist-info/METADATA
yaflux-0.3.2.dist-info/WHEEL
yaflux-0.3.2.dist-info/licenses/LICENSE
yaflux-0.3.2.dist-info/RECORD
