Metadata-Version: 2.4
Name: yaflux
Version: 0.3.2
Summary: A lightweight, declarative framework for python analysis workflows.
Author-email: noam teyssier <22600644+noamteyssier@users.noreply.github.com>
License-File: LICENSE
Requires-Python: >=3.10
Provides-Extra: anndata
Requires-Dist: anndata>=0.7.6; extra == 'anndata'
Provides-Extra: full
Requires-Dist: anndata>=0.7.6; extra == 'full'
Requires-Dist: graphviz>=0.20.3; extra == 'full'
Requires-Dist: numpy>=1.24.0; extra == 'full'
Requires-Dist: pandas>=2.0.0; extra == 'full'
Requires-Dist: pyarrow>=18.0.0; extra == 'full'
Provides-Extra: io
Requires-Dist: anndata>=0.7.6; extra == 'io'
Requires-Dist: numpy>=1.24.0; extra == 'io'
Requires-Dist: pandas>=2.0.0; extra == 'io'
Requires-Dist: pyarrow>=18.0.0; extra == 'io'
Provides-Extra: numpy
Requires-Dist: numpy>=1.24.0; extra == 'numpy'
Provides-Extra: pandas
Requires-Dist: pandas>=2.0.0; extra == 'pandas'
Requires-Dist: pyarrow>=18.0.0; extra == 'pandas'
Provides-Extra: viz
Requires-Dist: graphviz>=0.20.3; extra == 'viz'
